linux_api/__init__.py
linux_api/config.env
linux_api/requirements.txt
linux_api/server.py
linux_api/start.py
linux_api/start.sh
linux_api/start_debug.sh
linux_api/api/endpoints/admin_endpoints.py
linux_api/api/endpoints/mixed_endpoints.py
linux_api/api/endpoints/system_endpoints.py
linux_api/api/endpoints/unauthenticated_endpoints.py
linux_api/api/endpoints/user_endpoints.py
linux_api/core_functions/auth.py
linux_api/core_functions/infos.py
linux_api/core_functions/limiter.py
linux_api/core_functions/load_monitor.py
linux_api/core_functions/threads.py
linux_api/core_functions/user_database.py
linux_api/linux_api.egg-info/PKG-INFO
linux_api/linux_api.egg-info/SOURCES.txt
linux_api/linux_api.egg-info/dependency_links.txt
linux_api/linux_api.egg-info/entry_points.txt
linux_api/linux_api.egg-info/requires.txt
linux_api/linux_api.egg-info/top_level.txt
linux_api-2.0.0.dist-info/METADATA
linux_api-2.0.0.dist-info/WHEEL
linux_api-2.0.0.dist-info/entry_points.txt
linux_api-2.0.0.dist-info/top_level.txt
linux_api-2.0.0.dist-info/RECORD
